AUTHORS
LICENSE
MANIFEST.in
README.rst
setup.py
django_rblog.egg-info/PKG-INFO
django_rblog.egg-info/SOURCES.txt
django_rblog.egg-info/dependency_links.txt
django_rblog.egg-info/not-zip-safe
django_rblog.egg-info/requires.txt
django_rblog.egg-info/top_level.txt
docs/Makefile
docs/source/advanced.rst
docs/source/changelog.rst
docs/source/conf.py
docs/source/configuration.rst
docs/source/getting-involved.rst
docs/source/index.rst
docs/source/installation.rst
docs/source/overview.rst
docs/source/settings.rst
docs/source/todo.rst
docs/source/use-cases.rst
rblog/__init__.py
rblog/admin.py
rblog/feeds.py
rblog/forms.py
rblog/models.py
rblog/tests.py
rblog/urls.py
rblog/views.py
rblog/management/__init__.py
rblog/management/commands/__init__.py
rblog/management/commands/disqus_comments.py
rblog/migrations/0001_initial.py
rblog/migrations/0002_auto__del_comments__del_field_post_thread_id.py
rblog/migrations/0003_auto__add_comments__add_field_post_thread_id.py
rblog/migrations/0004_auto__chg_field_post_creation_date.py
rblog/migrations/0005_auto__add_field_post_image__add_field_post_highlighted.py
rblog/migrations/0006_auto__add_field_post_category.py
rblog/migrations/0007_auto__del_field_post_category.py
rblog/migrations/0008_auto__add_field_post_category.py
rblog/migrations/0009_auto__del_field_post_category.py
rblog/migrations/0010_auto.py
rblog/migrations/0011_auto__chg_field_post_slug.py
rblog/migrations/0012_auto__add_field_post_lang.py
rblog/migrations/0013_auto__add_field_post_canonical__add_unique_post_slug.py
rblog/migrations/0014_auto__add_field_post_robots.py
rblog/migrations/0015_auto__add_field_post_redirect.py
rblog/migrations/0016_auto__add_field_post_ptype.py
rblog/migrations/__init__.py
rblog/templates/site_base.html
rblog/templates/rblog/_base_breadcrumbs.html
rblog/templates/rblog/_base_metas.html
rblog/templates/rblog/_base_metas_seo.html
rblog/templates/rblog/_base_pagination.html
rblog/templates/rblog/_blog_archive.html
rblog/templates/rblog/_post_comments.html
rblog/templates/rblog/_post_footer.html
rblog/templates/rblog/_post_header.html
rblog/templates/rblog/_post_images.html
rblog/templates/rblog/_post_mainimage.html
